Metadata-Version: 1.0
Name: halfpipe
Version: 0.4
Summary: Functional Programming Tools
Home-page: https://github.com/migloo/halfpipe
Author: migloo
Author-email: migloo@gmail.com
License: MIT
Platform: UNKNOWN
